tests/__init__.py
tests/test_create_channel.py
tests/test_create_community_post.py
tests/test_create_community_post_sub_channel.py
tests/test_create_sub_channels.py
tests/test_create_video.py
tests/test_create_video_sub_channel.py
tests/test_delete_channel.py
tests/test_delete_sub_channel.py
tests/test_download_thumbnail.py
tests/test_download_video.py
tests/test_edit_channel.py
tests/test_edit_sub_channel.py
tests/test_get_all_video_stats_from_channel.py
tests/test_get_channel_id.py
tests/test_get_channel_stats.py
tests/test_get_my_channel_handle.py
tests/test_get_my_channel_id.py
tests/test_get_my_channel_stats.py
tests/test_get_my_videos_stats.py
tests/test_get_video_stats.py
tests/test_list_all_channels.py
tests/test_switch_to_sub_channel.py
youtube_selenium_py/__init__.py
youtube_selenium_py/classes.py
youtube_selenium_py/utils/__init__.py
youtube_selenium_py/utils/generic_utils.py
youtube_selenium_py/youtube/__init__.py
youtube_selenium_py/youtube/all_video_stats_from_channel.py
youtube_selenium_py/youtube/create_channel.py
youtube_selenium_py/youtube/create_community_post.py
youtube_selenium_py/youtube/create_sub_channels.py
youtube_selenium_py/youtube/create_video.py
youtube_selenium_py/youtube/delete_channel.py
youtube_selenium_py/youtube/download_thumbnail.py
youtube_selenium_py/youtube/download_video.py
youtube_selenium_py/youtube/edit_channel.py
youtube_selenium_py/youtube/get_all_video_stats_from_channel.py
youtube_selenium_py/youtube/get_channel_id.py
youtube_selenium_py/youtube/get_channel_stats.py
youtube_selenium_py/youtube/get_my_channel_handle.py
youtube_selenium_py/youtube/get_my_videos_stats.py
youtube_selenium_py/youtube/get_video_stats.py
youtube_selenium_py/youtube/list_all_channels.py
youtube_selenium_py/youtube/sign_into_youtube_channel.py
youtube_selenium_py/youtube/switch_to_sub_channel.py
youtube_selenium_py-1.0.9.dist-info/LICENSE
youtube_selenium_py-1.0.9.dist-info/METADATA
youtube_selenium_py-1.0.9.dist-info/WHEEL
youtube_selenium_py-1.0.9.dist-info/top_level.txt
youtube_selenium_py-1.0.9.dist-info/RECORD
