Metadata-Version: 2.1
Name: youtube_selenium_py
Version: 1.0.9
Summary: A Python package to create youtube channels, sub channels, upload videos, create community posts, edit channel, delete channel, and so much more.
Home-page: https://github.com/Automa-Automations/youtube_selenium_py
Author: William Ferns
Author-email: business@agnostica.site
License: MIT
Project-URL: Bug Reports, https://github.com/Automa-Automations/youtube_selenium_py/issues
Project-URL: Source, https://github.com/Automa-Automations/youtube_selenium_py
Project-URL: Automa Automations, https://github.com/Automa-Automations
Keywords: youtube,API,video,channel,upload,statistics,python,development,selenium
Classifier: Development Status :: 3 - Alpha
Classifier: Intended Audience :: Developers
Classifier: License :: OSI Approved :: MIT License
Classifier: Programming Language :: Python :: 3
Classifier: Programming Language :: Python :: 3.6
Classifier: Programming Language :: Python :: 3.7
Classifier: Programming Language :: Python :: 3.8
Classifier: Programming Language :: Python :: 3.9
License-File: LICENSE
Requires-Dist: attrs ==23.2.0
Requires-Dist: certifi ==2024.2.2
Requires-Dist: cffi ==1.16.0
Requires-Dist: charset-normalizer ==3.3.2
Requires-Dist: cryptography ==42.0.5
Requires-Dist: docutils ==0.20.1
Requires-Dist: h11 ==0.14.0
Requires-Dist: idna ==3.6
Requires-Dist: importlib-metadata ==7.1.0
Requires-Dist: jaraco.classes ==3.4.0
Requires-Dist: jaraco.context ==5.1.0
Requires-Dist: jaraco.functools ==4.0.0
Requires-Dist: jeepney ==0.8.0
Requires-Dist: keyring ==25.1.0
Requires-Dist: markdown-it-py ==3.0.0
Requires-Dist: mdurl ==0.1.2
Requires-Dist: more-itertools ==10.2.0
Requires-Dist: nh3 ==0.2.17
Requires-Dist: outcome ==1.3.0.post0
Requires-Dist: pkginfo ==1.10.0
Requires-Dist: pycparser ==2.22
Requires-Dist: Pygments ==2.17.2
Requires-Dist: PySocks ==1.7.1
Requires-Dist: python-dotenv ==1.0.1
Requires-Dist: pytube ==15.0.0
Requires-Dist: readme-renderer ==43.0
Requires-Dist: requests ==2.31.0
Requires-Dist: requests-toolbelt ==1.0.0
Requires-Dist: rfc3986 ==2.0.0
Requires-Dist: rich ==13.7.1
Requires-Dist: SecretStorage ==3.3.3
Requires-Dist: selenium ==4.19.0
Requires-Dist: setuptools ==69.2.0
Requires-Dist: sniffio ==1.3.1
Requires-Dist: sortedcontainers ==2.4.0
Requires-Dist: trio ==0.25.0
Requires-Dist: trio-websocket ==0.11.1
Requires-Dist: twine ==5.0.0
Requires-Dist: typing-extensions ==4.10.0
Requires-Dist: undetected-chromedriver ==3.5.5
Requires-Dist: urllib3 ==2.2.1
Requires-Dist: websockets ==12.0
Requires-Dist: wsproto ==1.2.0
Requires-Dist: zipp ==3.18.1
